shawon_mt5_automation/__init__.py
shawon_mt5_automation/core.py
shawon_mt5_automation-2.2.3.dist-info/METADATA
shawon_mt5_automation-2.2.3.dist-info/WHEEL
shawon_mt5_automation-2.2.3.dist-info/top_level.txt
shawon_mt5_automation-2.2.3.dist-info/RECORD
