Metadata-Version: 2.1
Name: shawon-mt5-automation
Version: 2.2.3
Summary: A Flask webhook server to automate MetaTrader 5 trading based on TradingView signals with configurable settings and API key authentication.
Home-page: https://github.com/yourusername/mt5-webhook-trader
Author: Mahmudul Haque Shawon
Author-email: haquemahmudul600@gmail.com
Classifier: Programming Language :: Python :: 3
Classifier: License :: OSI Approved :: MIT License
Classifier: Operating System :: OS Independent
Classifier: Development Status :: 3 - Alpha
Classifier: Intended Audience :: Developers
Classifier: Intended Audience :: Financial and Insurance Industry
Classifier: Topic :: Office/Business :: Financial :: Investment
Classifier: Topic :: Software Development :: Libraries :: Python Modules
Requires-Python: >=3.7
Requires-Dist: Flask>=2.0.0
Requires-Dist: MetaTrader5>=5.0.0
